iptables_stats/__init__.py
iptables_stats/__main__.py
iptables_stats/config.py
iptables_stats/iptables_stats.py
iptables_stats/mqtt.py
iptables_stats/sinks.py
iptables_stats/reading_modules/__init__.py
iptables_stats/reading_modules/dummy.py
iptables_stats/reading_modules/ipset.py
iptables_stats/reading_modules/iptables.py
iptables_stats-1.0.1.dist-info/METADATA
iptables_stats-1.0.1.dist-info/WHEEL
iptables_stats-1.0.1.dist-info/entry_points.txt
iptables_stats-1.0.1.dist-info/top_level.txt
iptables_stats-1.0.1.dist-info/RECORD
