Metadata-Version: 2.1
Name: iptables-stats
Version: 1.0.1
Summary: Periodically gathers and publishes statistics about iptables
Home-page: https://github.com/verybadsoldier/iptables_stats
Author: verybadsoldier
Author-email: vbs@springrts.de
Project-URL: Documentation, https://github.com/verybadsoldier/iptables_stats
Project-URL: Source, https://github.com/verybadsoldier/iptables_stats
Project-URL: Tracker, https://github.com/verybadsoldier/iptables_stats/issues
Platform: any
Classifier: Development Status :: 5 - Production/Stable
Classifier: Programming Language :: Python
Requires-Dist: ipsetpy ==0.0.1a3
Requires-Dist: paho-mqtt ==1.*
Requires-Dist: python-iptables ==1.*
Requires-Dist: pyptables ==1.*
Requires-Dist: schedule ==1.*
Requires-Dist: pyyaml ==6.*
Requires-Dist: importlib-metadata ; python_version < "3.8"
